moduleonly/__init__.py
moduleonly/plugin.py
nose_moduleonly-0.1.1.dist-info/DESCRIPTION.rst
nose_moduleonly-0.1.1.dist-info/METADATA
nose_moduleonly-0.1.1.dist-info/RECORD
nose_moduleonly-0.1.1.dist-info/WHEEL
nose_moduleonly-0.1.1.dist-info/entry_points.txt
nose_moduleonly-0.1.1.dist-info/metadata.json
nose_moduleonly-0.1.1.dist-info/top_level.txt
