Metadata-Version: 2.0
Name: nose-moduleonly
Version: 0.1.1
Summary: UNKNOWN
Home-page: https://github.com/craigds/nose-moduleonly
Author: Craig de Stigter
Author-email: craig.ds@gmail.com
License: BSD
Platform: UNKNOWN
Classifier: Intended Audience :: Developers
Classifier: Natural Language :: English
Classifier: Operating System :: OS Independent
Classifier: Topic :: Software Development :: Testing
Requires-Dist: Nose
